odoo/addons/stock_picking_report_internal_delivery_address/README.rst
odoo/addons/stock_picking_report_internal_delivery_address/__init__.py
odoo/addons/stock_picking_report_internal_delivery_address/__manifest__.py
odoo/addons/stock_picking_report_internal_delivery_address/i18n/it.po
odoo/addons/stock_picking_report_internal_delivery_address/i18n/stock_picking_report_internal_delivery_address.pot
odoo/addons/stock_picking_report_internal_delivery_address/models/__init__.py
odoo/addons/stock_picking_report_internal_delivery_address/models/stock_picking.py
odoo/addons/stock_picking_report_internal_delivery_address/readme/CONTRIBUTORS.md
odoo/addons/stock_picking_report_internal_delivery_address/readme/DESCRIPTION.md
odoo/addons/stock_picking_report_internal_delivery_address/static/description/icon.png
odoo/addons/stock_picking_report_internal_delivery_address/static/description/index.html
odoo/addons/stock_picking_report_internal_delivery_address/tests/__init__.py
odoo/addons/stock_picking_report_internal_delivery_address/tests/test_stock_picking_report_internal_delivery_address.py
odoo_addon_stock_picking_report_internal_delivery_address-18.0.1.0.0.2.dist-info/METADATA
odoo_addon_stock_picking_report_internal_delivery_address-18.0.1.0.0.2.dist-info/WHEEL
odoo_addon_stock_picking_report_internal_delivery_address-18.0.1.0.0.2.dist-info/top_level.txt
odoo_addon_stock_picking_report_internal_delivery_address-18.0.1.0.0.2.dist-info/RECORD
